lvs/__init__.py
lvs/cli.py
lvs/http_ext.py
lvs/save_ext.py
lvs/stream_server.py
lvs/view_ext.py
lvs/res/__init__.py
lvs/res/config.toml
lvs/res/cascade_classifiers/haarcascade_frontalface_default.xml
lvs/templates/index.html
lvs/video_streamer/__init__.py
lvs/video_streamer/dataclass_objects.py
lvs/video_streamer/socket_utils.py
lvs/video_streamer/video_streamer.py
lvs-1.0.dist-info/LICENSE
lvs-1.0.dist-info/METADATA
lvs-1.0.dist-info/WHEEL
lvs-1.0.dist-info/entry_points.txt
lvs-1.0.dist-info/top_level.txt
lvs-1.0.dist-info/RECORD
