Metadata-Version: 2.1
Name: lvs
Version: 1.0
Summary: Stream video from camera or video file to devices on your local network
Home-page: https://github.com/ksharshveer/lvs
Author: Harshveer Singh
Author-email: ksharshveer@gmail.com
License: MIT
Platform: UNKNOWN
Classifier: Programming Language :: Python :: 3
Classifier: License :: OSI Approved :: MIT License
Classifier: Operating System :: OS Independent
Requires-Python: >=3.7
Requires-Dist: opencv-python
Requires-Dist: click
Requires-Dist: toml
Requires-Dist: flask
